README.md
setup.py
crimpl/__init__.py
crimpl/common.py
crimpl/localthread.py
crimpl/remoteslurm.py
crimpl/remotethread.py
crimpl.egg-info/PKG-INFO
crimpl.egg-info/SOURCES.txt
crimpl.egg-info/dependency_links.txt
crimpl.egg-info/requires.txt
crimpl.egg-info/top_level.txt