Metadata-Version: 2.1
Name: crimpl
Version: 0.2.0
Summary: Compute Resources Made Simple
Home-page: https://www.github.com/kecnry/crimpl
Author: Kyle Conroy
Author-email: kyleconroy@gmail.com
License: UNKNOWN
Download-URL: https://github.com/kecnry/crimpl/tarball/0.2.0
Platform: UNKNOWN
Classifier: Development Status :: 1 - Planning
Classifier: Intended Audience :: Science/Research
Classifier: License :: OSI Approved :: GNU General Public License v3 (GPLv3)
Classifier: Natural Language :: English
Classifier: Operating System :: OS Independent
Classifier: Programming Language :: Python :: 2.7
Classifier: Programming Language :: Python :: 3.6
Classifier: Topic :: Scientific/Engineering
Classifier: Topic :: Software Development :: Libraries :: Python Modules
